{
  "Department": "Massachusetts Department of Health",
  "State": "Massachusetts",
  "Type": "State",
  "YouTube Channel": "https://www.youtube.com/@MassDPH",
  "channel_name": "MassDPH",
  "subscriber_count": "4900",
  "video_count": "953",
  "Video URL": "https://www.youtube.com/watch?v=S6WZxmGcQwk",
  "Video Title": "Learn About Safe Storage of Marijuana",
  "Video Length": "00:00:15",
  "Seconds": "15.0",
  "Views": "277.0",
  "Matched Keywords": "marijuana",
  "Published Date": "2018-09-24T00:00:00",
  "Year": "2018",
  "Like Count": "0.0",
  "Comment Count / Disabled": "0",
  "Cannabis Status (at video date)": "Recreational"
}